{
  "id": "1961456829381993777",
  "content": "<p data-pid=\"A5Rc8VL7\">文学是要基于现实的，和现实不同，得有好处。否则就会降低代入感和阅读体验。</p><p data-pid=\"81ivawgb\">成为双性人没有明显的好处，但对于绝大多数人来说都是非常远离现实的，所以双性人设定火不了。</p>",
  "excerpt": "文学是要基于现实的，和现实不同，得有好处。否则就会降低代入感和阅读体验。 成为双性人没有明显的好处，但对于绝大多数人来说都是非常远离现实的，所以双性人设定火不了。",
  "voteupCount": 3,
  "commentCount": 1,
  "favlistsCount": 1,
  "createdTime": "2025-10-14 07:42",
  "updatedTime": "2025-10-14 07:42",
  "author": {
    "id": "f3e9d8525e2df1e48f1c6baacf1ec822",
    "name": "CHROM",
    "headline": "",
    "avatarUrl": "https://pic1.zhimg.com/v2-e6396f40dc90b3a74a6ca5e881093d88_l.jpg?source=1def8aca"
  },
  "hotComment": null,
  "questionId": "1954309121877731241",
  "crawledAt": "2026-01-16T18:43:49.956Z"
}