{
  "id": "3490284611",
  "content": "<p data-pid=\"ddy7z7Rd\">如果能选择，我百分百选择做女人，即便是孤独一生</p>",
  "excerpt": "如果能选择，我百分百选择做女人，即便是孤独一生",
  "voteupCount": 4,
  "commentCount": 5,
  "createdTime": 1715062709,
  "updatedTime": 1715062709,
  "author": {
    "id": "828aaea5b3af954d4e1d0bf7b9f4021b",
    "name": "baby 荳",
    "headline": "一只想变成喵的mtf",
    "avatarUrl": "https://pica.zhimg.com/v2-d87f44b26b8040ed77d7ca808d2941f3_l.jpg?source=1def8aca"
  },
  "hotComment": null,
  "questionId": "655076235",
  "crawledAt": "2026-01-14T22:10:32.963Z"
}