{
  "id": "2147515711",
  "content": "<div class=\"css-376mun\"><span id=\"content\"><span class=\"RichText ztext CopyrightRichText-richText css-10o75c2\" options=\"[object Object]\" itemprop=\"text\"><p data-first-child=\"\" data-pid=\"rG-pmbBr\">不会。</p><p data-pid=\"8_9knDNT\">但是我们可能会抢同一个人。</p></span><span id=\"VirtualCatalogAnchorPoint\"></span></span></div>",
  "excerpt": "不会。\n\n但是我们可能会抢同一个人。",
  "voteupCount": 0,
  "commentCount": 0,
  "createdTime": "2021-09-30 00:29",
  "updatedTime": null,
  "author": {
    "id": "",
    "name": ""
  },
  "source": "ssr",
  "questionId": "317230323",
  "crawledAt": "2026-01-15T05:50:37.110Z"
}