{
  "id": "1420219983",
  "content": "<p data-pid=\"BT2iZ9q4\">澡堂洗澡去</p>",
  "excerpt": "澡堂洗澡去",
  "voteupCount": 1,
  "commentCount": 1,
  "favlistsCount": 0,
  "createdTime": "2020-08-19 13:28",
  "updatedTime": "2020-08-19 13:28",
  "author": {
    "id": "afb0e004e4cb166b8ca1528b3d13b009",
    "name": "可耻的匿了",
    "headline": "",
    "avatarUrl": "https://pica.zhimg.com/v2-abed1a8c04700ba7d72b45195223e0ff_l.jpg?source=1def8aca"
  },
  "hotComment": null,
  "questionId": "414852886",
  "crawledAt": "2026-01-15T07:59:08.517Z"
}