{
  "id": "2089213148",
  "content": "<div class=\"css-376mun\"><span id=\"content\"><span class=\"RichText ztext CopyrightRichText-richText css-10o75c2\" options=\"[object Object]\" itemprop=\"text\"><p data-first-child=\"\" data-pid=\"vXFSpMZ_\">一定换成男孩子，来一本纪实向bl和女孩子可以正经来一场bg。最后梦醒了再变回去，来一场gl就完美了。</p><p data-pid=\"1mmJlRBN\">挺好奇男性版自己的，最好在自我研究一下</p></span><span id=\"VirtualCatalogAnchorPoint\"></span></span></div>",
  "excerpt": "一定换成男孩子，来一本纪实向bl和女孩子可以正经来一场bg。最后梦醒了再变回去，来一场gl就完美了。\n\n挺好奇男性版自己的，最好在自我研究一下",
  "voteupCount": 0,
  "commentCount": 0,
  "createdTime": "2021-08-28 07:54",
  "updatedTime": null,
  "author": {
    "id": "",
    "name": ""
  },
  "source": "ssr",
  "questionId": "482695427",
  "crawledAt": "2026-01-15T05:52:26.546Z"
}