{
  "id": "1673380701",
  "content": "<p data-pid=\"eY2MhabU\">自我觉得这并不是什么好兆头，也不是什么女性崛起了的征兆，而恰恰是资本家用来收割女性的工具。</p><p data-pid=\"83YWItyO\">男性女性化恰恰诞生于男权思想比较严重的亚洲，这若还能代表女性崛起岂不是滑天下之大稽，北欧男女高度平等了吧，也没出现这种情况。只能说资本太过于猖獗，唯利是图。觉得女性的钱好赚，就搞出一些符合女性口味的东西，而近几年看来是越来越猖獗了，连陈情令这种耽美剧直接就放电视上演，不是说不能演，麻烦你不要顺势炒作行不行，炒了还不说，还要夹带私货，搞几个后援，顺带一波周边，甚至再来几场直播带货，钞票就哗哗啦啦进了他自己的口袋，这样赚钱还真的是快呀。</p><p data-pid=\"r41qUTNf\">还别说，我真的挺讨厌这种鼓吹消费主义，收割女性的做派。我不懂经济学，难道经济真的非得这样才能发展？</p>",
  "excerpt": "自我觉得这并不是什么好兆头，也不是什么女性崛起了的征兆，而恰恰是资本家用来收割女性的工具。 男性女性化恰恰诞生于男权思想比较严重的亚洲，这若还能代表女性崛起岂不是滑天下之大稽，北欧男女高度平等了吧，也没出现这种情况。只能说资本太过于猖獗，唯利是图。觉得女性的钱好赚，就搞出一些符合女性口味的东西，而近几年看来是越来越猖獗了，连陈情令这种耽美剧直接就放电视上演，不是说不能演，麻烦你不要顺势炒作行不行…",
  "voteupCount": 10,
  "commentCount": 3,
  "favlistsCount": 1,
  "createdTime": "2021-01-12 01:00",
  "updatedTime": "2021-01-12 01:32",
  "author": {
    "id": "0",
    "name": "匿名用户",
    "headline": "",
    "avatarUrl": "https://pica.zhimg.com/v2-d41c2ceaed8f51999522f903672a521f_l.jpg?source=1def8aca"
  },
  "hotComment": null,
  "questionId": "432131334",
  "crawledAt": "2026-01-17T05:23:18.086Z"
}