{
  "id": "3441905661",
  "content": "<div class=\"css-376mun\"><span id=\"content\"><span class=\"RichText ztext CopyrightRichText-richText css-119fve5\" options=\"[object Object]\" itemprop=\"text\"><p data-first-child=\"\" data-pid=\"nQi_0FQX\">我感觉男变女远多于女变男，至少网上是这样。</p></span><span id=\"VirtualCatalogAnchorPoint\"></span></span></div>",
  "excerpt": "我感觉男变女远多于女变男，至少网上是这样。",
  "voteupCount": 1,
  "commentCount": 0,
  "createdTime": "2024-03-24 11:12",
  "updatedTime": null,
  "author": {
    "id": "fly-31-23-76",
    "name": "飞fly"
  },
  "source": "ssr",
  "questionId": "642724738",
  "crawledAt": "2026-01-15T06:32:57.605Z"
}