{
  "id": "2844281081",
  "content": "<p data-pid=\"tksDyJBB\">爱无关性别</p>",
  "excerpt": "爱无关性别",
  "voteupCount": 0,
  "commentCount": 0,
  "favlistsCount": 0,
  "createdTime": "2023-01-13 15:47",
  "updatedTime": "2023-01-13 15:47",
  "author": {
    "id": "89e3c6a3c09dfbb3b05be7cf4402e054",
    "name": "saha",
    "headline": "",
    "avatarUrl": "https://picx.zhimg.com/v2-2731c7902cba93e738df5ed604e052f0_l.jpg?source=1def8aca"
  },
  "hotComment": null,
  "questionId": "576269787",
  "crawledAt": "2026-01-16T18:02:59.389Z"
}