{
  "id": "574001785",
  "content": "<div class=\"css-376mun\"><span id=\"content\"><span class=\"RichText ztext CopyrightRichText-richText css-10o75c2\" options=\"[object Object]\" itemprop=\"text\"><p data-first-child=\"\" data-pid=\"jlXcEiIA\">刚看了别人的科普，就说同性恋那块吧。不接受那样的自己，为什么可以喜欢女性也可以喜欢男性的时候，要选一条坎坷的路来走。</p></span><span id=\"VirtualCatalogAnchorPoint\"></span></span></div>",
  "excerpt": "刚看了别人的科普，就说同性恋那块吧。不接受那样的自己，为什么可以喜欢女性也可以喜欢男性的时候，要选一条坎坷的路来走。",
  "voteupCount": 0,
  "commentCount": 2,
  "createdTime": "2019-01-14 16:40",
  "updatedTime": null,
  "author": {
    "id": "",
    "name": ""
  },
  "source": "ssr",
  "questionId": "308904511",
  "crawledAt": "2026-01-16T18:59:21.847Z"
}