{
  "id": "2357755679",
  "content": "<div class=\"css-376mun\"><span id=\"content\"><span class=\"RichText ztext CopyrightRichText-richText css-119fve5\" options=\"[object Object]\" itemprop=\"text\"><p data-first-child=\"\" data-pid=\"eIzXB5P-\">不一定是先天的，也有各种外界因素影响。包括但是不限于家庭，朋友，社会环境。如果真的觉得自己的性别不适合自己，不妨试试看想象一下自己用另一个性别好好认真的生活一天。</p><p data-pid=\"rdQVqWpn\">如果觉得自己是先天的，可以试着回想一下自己到底是什么时候有这种念头，为什么会有这种念头，如果解决了这种念头会更好嘛</p><p data-pid=\"aEAz0qki\">不过，基于题主问得是“一定是先天的吗”那答案是否定的，因为自己的成长历程，青春期<span><a class=\"RichContent-EntityWord css-b7erz1\" data-za-not-track-link=\"true\" data-paste-text=\"true\" href=\"https://zhida.zhihu.com/search?content_id=458765541&amp;content_type=Answer&amp;match_order=1&amp;q=%E7%AC%AC%E4%BA%8C%E6%80%A7%E5%BE%81&amp;zhida_source=entity\" target=\"_blank\">第二性征<svg width=\"10px\" height=\"10px\" viewBox=\"0 0 16 16\" class=\"ZDI ZDI--FourPointedStar16 css-1dvsrp\" fill=\"currentColor\"><path d=\"m5.068 9.267-3.08-.77a.512.512 0 0 1 0-.994l3.08-.77a2.289 2.289 0 0 0 1.665-1.665l.77-3.08a.512.512 0 0 1 .994 0l.77 3.08c.205.82.845 1.46 1.665 1.665l3.08.77a.512.512 0 0 1 0 .994l-3.08.77a2.29 2.29 0 0 0-1.665 1.665l-.77 3.08a.512.512 0 0 1-.994 0l-.77-3.08a2.289 2.289 0 0 0-1.665-1.665Z\"></path></svg></a></span>的发育〈不特指〉所产生这种想法是很多很多的，不用刻意去遮掩自己的想法，如果能说出去，看看人家能不能接受哥哥，静下心一起说说话，聊聊这些东西就是最好的啦</p><p data-pid=\"KCkgVwlp\">也祝哥哥生活开心喔</p></span><span id=\"VirtualCatalogAnchorPoint\"></span></span></div>",
  "excerpt": "不一定是先天的，也有各种外界因素影响。包括但是不限于家庭，朋友，社会环境。如果真的觉得自己的性别不适合自己，不妨试试看想象一下自己用另一个性别好好认真的生活一天。\n\n如果觉得自己是先天的，可以试着回想一下自己到底是什么时候有这种念头，为什么会有这种念头，如果解决了这种念头会更好嘛\n\n不过，基于题主问得是“一定是先天的吗”那答案是否定的，因为自己的成长历程，青春期第二性征的发育〈不特指〉所产生这种想法是很多很多的，不用刻意去遮掩自己的想法，如果能说出去，看看人家能不能接受哥哥，静下心一起说说话，聊聊这些东西就是最好的啦\n\n也祝哥哥生活开心喔",
  "voteupCount": 41,
  "commentCount": 1,
  "createdTime": "2022-02-21 09:08",
  "updatedTime": null,
  "author": {
    "id": "jiu-zhou-jun-63",
    "name": "北白川汐厸"
  },
  "source": "ssr",
  "questionId": "517575592",
  "crawledAt": "2026-01-17T01:13:07.911Z"
}