{
  "id": "2452184549",
  "content": "<p data-pid=\"TkhZASFe\">从上海女同性侵案那个女方女友的态度就能看出，女同流氓在面对同性的时候有多狠，很多细节都能看出女同对同伴的控制欲特别强，直接跟警察吼 她不可能对男性有感觉。我早觉得这些事应该揭露一下，绝对不是什么正常的事情，硬让对方改变性取向的感觉。女同也会强奸女性，当然是手动挡；女同也会精神控制女性；一个非女性同性恋在长时间被摩擦敏感部位，也可能有感觉被迫性转，剩下的自己琢磨女人对女人的pua更很。</p>",
  "excerpt": "从上海女同性侵案那个女方女友的态度就能看出，女同流氓在面对同性的时候有多狠，很多细节都能看出女同对同伴的控制欲特别强，直接跟警察吼 她不可能对男性有感觉。我早觉得这些事应该揭露一下，绝对不是什么正常的事情，硬让对方改变性取向的感觉。女同也会强奸女性，当然是手动挡；女同也会精神控制女性；一个非女性同性恋在长时间被摩擦敏感部位，也可能有感觉被迫性转，剩下的自己琢磨女人对女人的pua更很。",
  "voteupCount": 2,
  "commentCount": 2,
  "favlistsCount": 0,
  "createdTime": "2022-04-22 08:09",
  "updatedTime": "2022-04-23 12:58",
  "author": {
    "id": "6ae8e983d02f0c3af3c5dcfa9a4a3a65",
    "name": "东尼森林原人",
    "headline": "",
    "avatarUrl": "https://pic1.zhimg.com/v2-c9fb4172440d9d45435e8308127c24a6_l.jpg?source=1def8aca"
  },
  "hotComment": null,
  "questionId": "517575592",
  "crawledAt": "2026-01-17T01:13:02.941Z"
}