{
  "id": "1948804656600945644",
  "content": "<div class=\"css-376mun\"><span id=\"content\"><span class=\"RichText ztext CopyrightRichText-richText css-10o75c2\" options=\"[object Object]\" itemprop=\"text\"><p data-first-child=\"\" data-pid=\"XspFk36n\">我会给我好兄弟发福利，因为我的好兄弟都是女本位社会下的受害者，我想用我的身体去安慰他们，践行我<span><a class=\"RichContent-EntityWord css-b7erz1\" data-za-not-track-link=\"true\" data-paste-text=\"true\" href=\"https://zhida.zhihu.com/search?content_id=746260264&amp;content_type=Answer&amp;match_order=1&amp;q=%E7%B1%B3%E6%A0%BC%E9%81%93&amp;zhida_source=entity\" target=\"_blank\">米格道<svg width=\"10px\" height=\"10px\" viewBox=\"0 0 16 16\" class=\"ZDI ZDI--FourPointedStar16 css-1dvsrp\" fill=\"currentColor\"><path d=\"m5.068 9.267-3.08-.77a.512.512 0 0 1 0-.994l3.08-.77a2.289 2.289 0 0 0 1.665-1.665l.77-3.08a.512.512 0 0 1 .994 0l.77 3.08c.205.82.845 1.46 1.665 1.665l3.08.77a.512.512 0 0 1 0 .994l-3.08.77a2.29 2.29 0 0 0-1.665 1.665l-.77 3.08a.512.512 0 0 1-.994 0l-.77-3.08a2.289 2.289 0 0 0-1.665-1.665Z\"></path></svg></a></span>的终身追求。毕竟变女的，也就不被女本位社会压迫了，真实想法。当然如果我的好兄弟愿意不只是玩玩我而是跟我终身在一起的话那我也会对他好的。就这样。</p></span><span id=\"VirtualCatalogAnchorPoint\"></span></span></div>",
  "excerpt": "我会给我好兄弟发福利，因为我的好兄弟都是女本位社会下的受害者，我想用我的身体去安慰他们，践行我米格道的终身追求。毕竟变女的，也就不被女本位社会压迫了，真实想法。当然如果我的好兄弟愿意不只是玩玩我而是跟我终身在一起的话那我也会对他好的。就这样。",
  "voteupCount": 18,
  "author": {
    "id": "34376767",
    "name": "34376767"
  },
  "source": "ssr",
  "questionId": "1945084412325786905",
  "crawledAt": "2026-01-14T18:03:00.525Z",
  "createdTime": null,
  "updatedTime": null
}