{
  "id": "1983706357686350838",
  "content": "<div class=\"css-376mun\"><span id=\"content\"><span class=\"RichText ztext CopyrightRichText-richText css-10o75c2\" options=\"[object Object]\" itemprop=\"text\"><p data-first-child=\"\" data-pid=\"IuGr6leG\">住宿的话不愿意。。。尤其是长期的，我其实喜欢一个人住，最多父母。一想到大学的6人寝室不是让我带饭、就是占我座位、让我帮忙接水、时不时的还有人吸烟、突然抱腰（也不算性骚扰吧，就是那个男生经常玩游戏什么的兴奋了就抱住我，疑似以为我和他关系比较好，带饭也是他让我带的最多）尝试劝我停药（我家长都没说什么，建议你先戒烟）就好烦。。。给我安排同类的话也许好点吧？但是我真的不想掺和集体的事情，尤其是互相之间还不熟悉</p></span><span id=\"VirtualCatalogAnchorPoint\"></span></span></div>",
  "excerpt": "住宿的话不愿意。。。尤其是长期的，我其实喜欢一个人住，最多父母。一想到大学的6人寝室不是让我带饭、就是占我座位、让我帮忙接水、时不时的还有人吸烟、突然抱腰（也不算性骚扰吧，就是那个男生经常玩游戏什么的兴奋了就抱住我，疑似以为我和他关系比较好，带饭也是他让我带的最多）尝试劝我停药（我家长都没说什么，建议你先戒烟）就好烦。。。给我安排同类的话也许好点吧？但是我真的不想掺和集体的事情，尤其是互相之间还不熟悉",
  "voteupCount": 52,
  "author": {
    "id": "yun-duo-shang-de-mao-33-30",
    "name": "帆帆爱吃木桶饭"
  },
  "source": "ssr",
  "questionId": "1983670795965318726",
  "crawledAt": "2026-01-14T22:45:19.937Z",
  "createdTime": null,
  "updatedTime": null
}