{
  "id": "1991935608394896610",
  "content": "<p data-pid=\"N3DyV44X\">同居的女朋友就是已经做了变性手术的awa</p>",
  "excerpt": "同居的女朋友就是已经做了变性手术的awa",
  "voteupCount": 1,
  "commentCount": 0,
  "createdTime": 1767694457,
  "updatedTime": 1767694457,
  "author": {
    "id": "bc1e8a898dfb8fa6ded7b1583d73ef62",
    "name": "术后普通人",
    "headline": "一个13岁吃药，18岁做了srs的mtf",
    "avatarUrl": "https://picx.zhimg.com/v2-ce73bce7de82fb39dc02f041135afdd6_l.jpg?source=1def8aca"
  },
  "hotComment": null,
  "questionId": "1983670795965318726",
  "crawledAt": "2026-01-14T22:46:58.509Z"
}