{
  "id": "88229879",
  "content": "<p data-pid=\"dsIo7BhN\">泻药……首先，GID并不是病……不需要治愈</p><p data-pid=\"wP_eowuv\">就算“治愈”了GID，不过有些心灵深处的东西，是不会变的呢，比如性取向和社会上对性别的刻板印象。估计，还是会在社会上格格不入……</p><p data-pid=\"QGX3ENWi\">当然，如果包括少女心，性格，性取向什么的都能改变的话，那就感觉到，这个人，就不是我了。。。</p>",
  "excerpt": "泻药…首先，GID并不是病…不需要治愈 就算“治愈”了GID，不过有些心灵深处的东西，是不会变的呢，比如性取向和社会上对性别的刻板印象。估计，还是会在社会上格格不入… 当然，如果包括少女心，性格，性取向什么的都能改变的话，那就感觉到，这个人，就不是我了。。。",
  "voteupCount": 17,
  "commentCount": 4,
  "favlistsCount": 9,
  "createdTime": "2016-02-26 12:30",
  "updatedTime": "2016-02-26 12:30",
  "author": {
    "id": "8ea6b53f5afb6f82138cb4632f63e36f",
    "name": "脸娘",
    "headline": "唔，一只萌萌的项目经理",
    "avatarUrl": "https://picx.zhimg.com/v2-57247ea573d4db1a8f4418845e2e0ce8_l.jpg?source=1def8aca"
  },
  "hotComment": null,
  "questionId": "40733448",
  "crawledAt": "2026-01-16T17:56:36.603Z"
}