{
  "id": "561372297",
  "content": "<p data-pid=\"ya-LzGhX\">当然接受~我的专业这行都不收女性，太亏了，而且当男的催婚压力没那么大，也不用为了生孩子啥的牺牲工作，没有每个月的姨妈，想想就爽~</p>",
  "excerpt": "当然接受~我的专业这行都不收女性，太亏了，而且当男的催婚压力没那么大，也不用为了生孩子啥的牺牲工作，没有每个月的姨妈，想想就爽~",
  "voteupCount": 0,
  "commentCount": 0,
  "favlistsCount": 0,
  "createdTime": "2018-12-28 02:08",
  "updatedTime": "2018-12-28 02:08",
  "author": {
    "id": "0",
    "name": "匿名用户",
    "headline": "",
    "avatarUrl": "https://picx.zhimg.com/v2-d41c2ceaed8f51999522f903672a521f_l.jpg?source=1def8aca"
  },
  "hotComment": null,
  "questionId": "307212932",
  "crawledAt": "2026-01-15T05:47:30.438Z"
}