[
  {
    "url": "https://www.zhihu.com/api/v4/questions/362042241/similar-questions?include=data%5B*%5D.answer_count%2Cauthor%2Cfollower_count&limit=5",
    "type": "similar-questions",
    "timestamp": 1768588395485,
    "data": {
      "paging": {
        "is_end": true,
        "is_start": true,
        "next": "https://www.zhihu.com/api/v4/questions/362042241/similar-questions?include=data%5B%2A%5D.answer_count%2Cauthor%2Cfollower_count&limit=10&offset=10",
        "previous": "https://www.zhihu.com/api/v4/questions/362042241/similar-questions?include=data%5B%2A%5D.answer_count%2Cauthor%2Cfollower_count&limit=10&offset=0",
        "totals": 1
      },
      "data": [
        {
          "type": "question",
          "title": "挖矿他们说的gas费用是什么意思？",
          "question_type": "normal",
          "created": 1620285216,
          "updated_time": 1620285216,
          "url": "https://www.zhihu.com/api/v4/questions/458054074",
          "answer_count": 23,
          "comment_count": 0,
          "follower_count": 30,
          "relationship": {},
          "id": "458054074"
        }
      ]
    }
  }
]