{
  "id": "720761208",
  "content": "<p data-pid=\"xFpEmAQJ\">因为一切生物的生存本质都是为了繁衍。</p><p class=\"ztext-empty-paragraph\"><br/></p><p data-pid=\"m4ZKO9jO\">至于第三性等乱七八糟的事儿，</p><p data-pid=\"cVvx5llP\">都是人类有了高级思维后的非生物性的存在，</p><p data-pid=\"Wi3HmfqR\">之后，心理反向影响生理。</p>",
  "excerpt": "因为一切生物的生存本质都是为了繁衍。 至于第三性等乱七八糟的事儿， 都是人类有了高级思维后的非生物性的存在， 之后，心理反向影响生理。",
  "voteupCount": 3,
  "commentCount": 0,
  "favlistsCount": 0,
  "createdTime": "2019-06-19 09:47",
  "updatedTime": "2019-06-19 09:47",
  "author": {
    "id": "f83b49b80de5c26e44f0ad93cd093215",
    "name": "知乎用户wO4912",
    "headline": "",
    "avatarUrl": "https://picx.zhimg.com/v2-abed1a8c04700ba7d72b45195223e0ff_l.jpg?source=1def8aca"
  },
  "hotComment": null,
  "questionId": "330155561",
  "crawledAt": "2026-01-15T08:04:58.881Z"
}