{
  "title": "男女的性别差异体现在哪些地方?",
  "detail": "<div><span itemprop=\"text\">很明显或潜在差异 包括思想 社会认知</span><button type=\"button\" class=\"Button QuestionRichText-more FEfUrdfMIKpQDJDqkjte Button--plain fEPKGkUK5jyc4fUuT0QP\">显示全部 <span style=\"display: inline-flex; align-items: center;\">​<svg width=\"24\" height=\"24\" viewBox=\"0 0 24 24\" class=\"Zi Zi--ArrowDown\" fill=\"currentColor\"><path fill-rule=\"evenodd\" d=\"M17.776 10.517a.875.875 0 0 1-.248 1.212l-5.05 3.335a.875.875 0 0 1-.964 0L6.47 11.73a.875.875 0 1 1 .965-1.46l4.56 3.015 4.568-3.016a.875.875 0 0 1 1.212.248Z\" clip-rule=\"evenodd\"></path></svg></span></button></div>",
  "followerCount": 6,
  "answerCount": 3,
  "topics": [
    "性别",
    "女性",
    "性别差异",
    "性别平等",
    "社会性别"
  ],
  "url": "https://www.zhihu.com/question/321431987",
  "relatedQuestions": [
    {
      "id": "1923124163004044460",
      "title": "为什么男女的性别会有这么多的不同？",
      "answerCount": 1,
      "topics": []
    },
    {
      "id": "19646607",
      "title": "男女之间哪些特点是由性别差异引起的？",
      "answerCount": 2,
      "topics": []
    },
    {
      "id": "48058550",
      "title": "有什么是男女性别差异造成的认知错误?",
      "answerCount": 1,
      "topics": []
    }
  ],
  "answers": [
    {
      "id": "661995156",
      "voteupCount": 1,
      "author": "路人甲的已丙丁"
    },
    {
      "id": "1698807651",
      "voteupCount": 5,
      "author": "木马逐风"
    },
    {
      "id": "1299690504",
      "voteupCount": 0,
      "author": "上海ladyboy馨妍"
    }
  ],
  "crawledAt": "2026-01-16T19:14:00.989Z",
  "id": "321431987",
  "updatedAt": "2026-01-16T19:14:00.989Z"
}