{
  "id": "1914510831",
  "content": "<div class=\"css-376mun\"><span id=\"content\"><span class=\"RichText ztext CopyrightRichText-richText css-119fve5\" options=\"[object Object]\" itemprop=\"text\"><p data-first-child=\"\" data-pid=\"6c03ELAD\">保护【生物性别刻板印象】消除【社会性别刻板印象】，，防止居心不良的人，借用消除【社会刻板印象】的正义幌子，做着消【生物刻板印象】的事</p><figure data-size=\"normal\"><noscript><img src=\"https://pic1.zhimg.com/50/v2-b6c1fda72cdba00ef76a92d37ce5c8ad_720w.jpg?source=1def8aca\" data-rawwidth=\"1499\" data-rawheight=\"4032\" data-size=\"normal\" data-original-token=\"v2-b6c1fda72cdba00ef76a92d37ce5c8ad\" data-default-watermark-src=\"https://picx.zhimg.com/50/v2-3391a9ab5fd0e7e42fcf8b2fa29390f8_720w.jpg?source=1def8aca\" class=\"origin_image zh-lightbox-thumb\" width=\"1499\" data-original=\"https://picx.zhimg.com/v2-b6c1fda72cdba00ef76a92d37ce5c8ad_r.jpg?source=1def8aca\"/></noscript><div><img src=\"https://pic1.zhimg.com/80/v2-b6c1fda72cdba00ef76a92d37ce5c8ad_720w.webp?source=1def8aca\" data-rawwidth=\"1499\" data-rawheight=\"4032\" data-size=\"normal\" data-original-token=\"v2-b6c1fda72cdba00ef76a92d37ce5c8ad\" data-default-watermark-src=\"https://picx.zhimg.com/50/v2-3391a9ab5fd0e7e42fcf8b2fa29390f8_720w.jpg?source=1def8aca\" class=\"origin_image zh-lightbox-thumb lazy\" width=\"1499\" data-original=\"https://picx.zhimg.com/v2-b6c1fda72cdba00ef76a92d37ce5c8ad_r.jpg?source=1def8aca\" data-actualsrc=\"https://pic1.zhimg.com/50/v2-b6c1fda72cdba00ef76a92d37ce5c8ad_720w.jpg?source=1def8aca\" height=\"4032\" data-lazy-status=\"ok\"></div></figure><p></p></span><span id=\"VirtualCatalogAnchorPoint\"></span></span></div>",
  "excerpt": "保护【生物性别刻板印象】消除【社会性别刻板印象】，，防止居心不良的人，借用消除【社会刻板印象】的正义幌子，做着消【生物刻板印象】的事",
  "voteupCount": 3,
  "commentCount": 0,
  "createdTime": "2021-05-30 23:34",
  "updatedTime": null,
  "author": {
    "id": "cang-long-25-59",
    "name": "I FEELGOOD"
  },
  "source": "ssr",
  "questionId": "454380292",
  "crawledAt": "2026-01-15T07:45:16.636Z"
}