{
  "title": "抛开性的因素，人们是否更愿意与自己性别相同的人相处，对于男女都一样吗？",
  "detail": "",
  "followerCount": 1,
  "answerCount": 1,
  "topics": [
    "社交网络",
    "两性关系",
    "社交礼仪"
  ],
  "url": "https://www.zhihu.com/question/24191201",
  "relatedQuestions": [
    {
      "id": "603743400",
      "title": "男性和女性各自都有哪些性别相关的缺点?",
      "answerCount": 13,
      "topics": []
    },
    {
      "id": "51282323",
      "title": "一个人心理上存在性别之分吗？如果有的话影响因素大概有那些？",
      "answerCount": 4,
      "topics": []
    },
    {
      "id": "457164709",
      "title": "男女是否有基于性别本身的特质和思考问题的方式差异？如果有，社会规训对这部分的特质会有影响吗?",
      "answerCount": 12,
      "topics": []
    },
    {
      "id": "264629381",
      "title": "性别的定义是生理上还是心理上？",
      "answerCount": 26,
      "topics": []
    },
    {
      "id": "430731013",
      "title": "怎样看待那些总爱把女性性别有优势挂在嘴里的男生？",
      "answerCount": 8,
      "topics": []
    }
  ],
  "answers": [
    {
      "id": "361969909",
      "voteupCount": 1,
      "author": ""
    }
  ],
  "crawledAt": "2026-01-17T13:02:51.423Z",
  "id": "24191201",
  "updatedAt": "2026-01-17T13:02:51.423Z"
}