{
  "id": "1974217305350219555",
  "content": "<p data-pid=\"gqRc315u\">其实性别重置手术真……不……那么……疼</p>",
  "excerpt": "其实性别重置手术真…不…那么…疼",
  "voteupCount": 2,
  "commentCount": 0,
  "createdTime": 1763470084,
  "updatedTime": 1763470084,
  "author": {
    "id": "b7332430de1eef01c3de8eaf9cd91ff1",
    "name": "丸子丸子头",
    "headline": "网易云WanZ/公众号：丸子以及丸子是猫",
    "avatarUrl": "https://picx.zhimg.com/v2-ababf6b5c2d89b9445b9c206d18ee671_l.jpg?source=1def8aca"
  },
  "hotComment": null,
  "questionId": "1971826736569225640",
  "crawledAt": "2026-01-14T23:04:42.370Z"
}