{
  "title": "你是否愿意为了爱，去做变性手术？",
  "url": "https://www.zhihu.com/question/1985323635767010601",
  "source": "topic_feed:27814732",
  "needsFetch": false,
  "id": "1985323635767010601",
  "updatedAt": "2026-01-14T17:46:34.358Z",
  "crawledAt": "2026-01-14T17:46:34.357Z",
  "detail": "",
  "followerCount": 33,
  "topics": [
    "变性手术",
    "变性人生"
  ],
  "answerCount": 25,
  "relatedQuestions": [
    {
      "id": "1981326457616766471",
      "title": "有没有人做过变性手术来说一下感受？",
      "answerCount": 7,
      "topics": []
    },
    {
      "id": "1987770839429554973",
      "title": "你们都是如何说服父母同意你们做变性手术的?",
      "answerCount": 11,
      "topics": []
    }
  ],
  "answers": [
    {
      "id": "1988015163757069000",
      "voteupCount": 2,
      "author": "乡村七阿哥"
    },
    {
      "id": "1987214927648298448",
      "voteupCount": 1,
      "author": "东先生"
    },
    {
      "id": "1987453351378559434",
      "voteupCount": 1,
      "author": "啦什么啦"
    },
    {
      "id": "1987474454406787545",
      "voteupCount": 1,
      "author": "一叶知秋"
    },
    {
      "id": "1990603733197928149",
      "voteupCount": 0,
      "author": "脸娘"
    },
    {
      "id": "1986211760571716331",
      "voteupCount": 4,
      "author": "梁晨星"
    },
    {
      "id": "1994485906619524797",
      "voteupCount": 1,
      "author": "半个小女孩儿"
    },
    {
      "id": "1985328668294263484",
      "voteupCount": 20,
      "author": "温馨一梦"
    },
    {
      "id": "1985650552034590922",
      "voteupCount": 9,
      "author": "哆啦A梦"
    },
    {
      "id": "1985446844411691745",
      "voteupCount": 4,
      "author": "鸡蛋实验猿"
    },
    {
      "id": "1985463094143639838",
      "voteupCount": 1,
      "author": "行多久方为执着"
    },
    {
      "id": "1985457721860977680",
      "voteupCount": 0,
      "author": "Jennie"
    },
    {
      "id": "1985326034023888154",
      "voteupCount": 0,
      "author": "默默"
    },
    {
      "id": "1985703591462330415",
      "voteupCount": 0,
      "author": "娜妹"
    },
    {
      "id": "1985705372103754246",
      "voteupCount": 0,
      "author": "沈韬亮"
    },
    {
      "id": "1986713191254864971",
      "voteupCount": 0,
      "author": "诸神黄昏"
    },
    {
      "id": "1987281769540625739",
      "voteupCount": 0,
      "author": "black white"
    },
    {
      "id": "1987617666777761751",
      "voteupCount": 0,
      "author": "买买"
    },
    {
      "id": "1990185363315119535",
      "voteupCount": 0,
      "author": "娱乐的认真"
    },
    {
      "id": "1985325820831618269",
      "voteupCount": 0,
      "author": "苏楠"
    },
    {
      "id": "1990704716091520979",
      "voteupCount": 0,
      "author": "麻烦死了"
    },
    {
      "id": "1993863003016304559",
      "voteupCount": 0,
      "author": "有机人七"
    },
    {
      "id": "1994162129255825502",
      "voteupCount": 0,
      "author": "笑看红尘"
    },
    {
      "id": "1994427820705870334",
      "voteupCount": 0,
      "author": "精彩人生"
    }
  ]
}