{
  "title": "《素时纪》初审 复审 终审都是干嘛的？初审过了后边就OK了吗？",
  "detail": "",
  "followerCount": 2,
  "answerCount": 2,
  "topics": [
    "写作",
    "书籍",
    "编辑"
  ],
  "url": "https://www.zhihu.com/question/272142652",
  "relatedQuestions": [
    {
      "id": "544285574",
      "title": "起点上面有很多以日本为背景的网文  数量真的不少 可以直接举报吗 ？应该怎么举报？",
      "answerCount": 10,
      "topics": []
    },
    {
      "id": "452104696",
      "title": "有没有好看的历史同人文?",
      "answerCount": 1,
      "topics": []
    }
  ],
  "answers": [
    {
      "id": "367094451",
      "voteupCount": 0,
      "author": "小编不空"
    },
    {
      "id": "438529747",
      "voteupCount": 0,
      "author": ""
    }
  ],
  "crawledAt": "2026-01-16T18:47:17.814Z",
  "id": "272142652",
  "updatedAt": "2026-01-16T18:47:17.814Z"
}