{
  "id": "1954343583697073831",
  "content": "<p data-pid=\"ogcHJ_6J\">你是真的确定自己厌恶自己作为男性或者女性的身份，想要变性，还是只是深受外表主义困扰？如果是后者，我建议直接去做整形手术就可以了。说不定你整形成功以后人生就豁然开朗了，也不觉得自己非要变了。</p>",
  "excerpt": "你是真的确定自己厌恶自己作为男性或者女性的身份，想要变性，还是只是深受外表主义困扰？如果是后者，我建议直接去做整形手术就可以了。说不定你整形成功以后人生就豁然开朗了，也不觉得自己非要变了。",
  "voteupCount": 6,
  "commentCount": 0,
  "createdTime": "2025-09-24 16:37",
  "updatedTime": "2025-09-24 16:37",
  "author": {
    "id": "0bcfef7a2bb2be71ff44f7b5973038f0",
    "name": "波波",
    "headline": "梦想开Uber，北极大学失败学专业。",
    "avatarUrl": "https://picx.zhimg.com/v2-22dfe7094375e34e38695123acd219db_l.jpg?source=1def8aca"
  },
  "hotComment": null,
  "questionId": "1949067690992967828",
  "crawledAt": "2026-01-14T22:04:09.314Z"
}