{
  "id": "1955037105664275611",
  "content": "<div class=\"css-376mun\"><span id=\"content\"><span class=\"RichText ztext CopyrightRichText-richText css-10o75c2\" options=\"[object Object]\" itemprop=\"text\"><p data-first-child=\"\" data-pid=\"i7p-cku6\">虽然我不是学医的，可能说法也不太准确。</p><p data-pid=\"isxYQ-Qa\">估计很多大手术都是要脱光衣服的；你这还涉及到性器官，那估计手术时不仅要脱裤子、还要把你身上所有衣服全部脱光。</p><p data-pid=\"WwJeE6JA\">补充一点，说句很不好听的话，变性手术就是“开弓没有回头箭”，而且变完性后，结果是“男不男、女不女”的。变性后连月月友、怀孕生崽的能力都没有，除非你是女性假两性畸形，而真正的女假做的手术可不叫“变性手术”，而是“<span><a class=\"RichContent-EntityWord css-b7erz1\" data-za-not-track-link=\"true\" data-paste-text=\"true\" href=\"https://zhida.zhihu.com/search?content_id=749136949&amp;content_type=Answer&amp;match_order=1&amp;q=%E6%80%A7%E5%88%AB%E9%87%8D%E7%BD%AE%E6%89%8B%E6%9C%AF&amp;zhida_source=entity\" target=\"_blank\">性别重置手术<svg width=\"10px\" height=\"10px\" viewBox=\"0 0 16 16\" class=\"ZDI ZDI--FourPointedStar16 css-1dvsrp\" fill=\"currentColor\"><path d=\"m5.068 9.267-3.08-.77a.512.512 0 0 1 0-.994l3.08-.77a2.289 2.289 0 0 0 1.665-1.665l.77-3.08a.512.512 0 0 1 .994 0l.77 3.08c.205.82.845 1.46 1.665 1.665l3.08.77a.512.512 0 0 1 0 .994l-3.08.77a2.29 2.29 0 0 0-1.665 1.665l-.77 3.08a.512.512 0 0 1-.994 0l-.77-3.08a2.289 2.289 0 0 0-1.665-1.665Z\"></path></svg></a></span>”。</p></span><span id=\"VirtualCatalogAnchorPoint\"></span></span></div>",
  "excerpt": "虽然我不是学医的，可能说法也不太准确。\n\n估计很多大手术都是要脱光衣服的；你这还涉及到性器官，那估计手术时不仅要脱裤子、还要把你身上所有衣服全部脱光。\n\n补充一点，说句很不好听的话，变性手术就是“开弓没有回头箭”，而且变完性后，结果是“男不男、女不女”的。变性后连月月友、怀孕生崽的能力都没有，除非你是女性假两性畸形，而真正的女假做的手术可不叫“变性手术”，而是“性别重置手术”。",
  "voteupCount": 16,
  "author": {
    "id": "abccheng-yi",
    "name": "ABC成溢"
  },
  "source": "ssr",
  "questionId": "1925383409510908013",
  "crawledAt": "2026-01-14T17:37:14.639Z"
}